genprimers-0.0.1.dist-info/DESCRIPTION.rst
genprimers-0.0.1.dist-info/METADATA
genprimers-0.0.1.dist-info/RECORD
genprimers-0.0.1.dist-info/WHEEL
genprimers-0.0.1.dist-info/entry_points.txt
genprimers-0.0.1.dist-info/metadata.json
genprimers-0.0.1.dist-info/top_level.txt
lib/__init__.py
lib/genprimers.py
lib/list_module.py
lib/parse_args.py
lib/primers.py
lib/Probe/ProbePair.py
lib/Probe/ProbeSet.py
lib/Probe/Probes.py
lib/Probe/__init__.py
lib/Probe/Sequence/Aligner.py
lib/Probe/Sequence/__init__.py
lib/Probe/Thermo/DNAThermoModel.py
lib/Probe/Thermo/NNModel.py
lib/Probe/Thermo/__init__.py
lib/Report/Reporter.py
lib/Report/__init__.py
lib/templates/index.html
lib/templates/pairs.html
lib/templates/primers.html
lib/templates/site_libs/bootstrap-3.3.5/css/bootstrap-theme.css
lib/templates/site_libs/bootstrap-3.3.5/css/bootstrap-theme.css.map
lib/templates/site_libs/bootstrap-3.3.5/css/bootstrap-theme.min.css
lib/templates/site_libs/bootstrap-3.3.5/css/bootstrap.css
lib/templates/site_libs/bootstrap-3.3.5/css/bootstrap.css.map
lib/templates/site_libs/bootstrap-3.3.5/css/bootstrap.min.css
lib/templates/site_libs/bootstrap-3.3.5/css/cerulean.min.css
lib/templates/site_libs/bootstrap-3.3.5/css/cosmo.min.css
lib/templates/site_libs/bootstrap-3.3.5/css/flatly.min.css
lib/templates/site_libs/bootstrap-3.3.5/css/journal.min.css
lib/templates/site_libs/bootstrap-3.3.5/css/lumen.min.css
lib/templates/site_libs/bootstrap-3.3.5/css/paper.min.css
lib/templates/site_libs/bootstrap-3.3.5/css/readable.min.css
lib/templates/site_libs/bootstrap-3.3.5/css/sandstone.min.css
lib/templates/site_libs/bootstrap-3.3.5/css/simplex.min.css
lib/templates/site_libs/bootstrap-3.3.5/css/spacelab.min.css
lib/templates/site_libs/bootstrap-3.3.5/css/united.min.css
lib/templates/site_libs/bootstrap-3.3.5/css/yeti.min.css
lib/templates/site_libs/bootstrap-3.3.5/css/fonts/Lato.ttf
lib/templates/site_libs/bootstrap-3.3.5/css/fonts/LatoBold.ttf
lib/templates/site_libs/bootstrap-3.3.5/css/fonts/LatoItalic.ttf
lib/templates/site_libs/bootstrap-3.3.5/css/fonts/NewsCycle.ttf
lib/templates/site_libs/bootstrap-3.3.5/css/fonts/NewsCycleBold.ttf
lib/templates/site_libs/bootstrap-3.3.5/css/fonts/OpenSans.ttf
