Metadata-Version: 2.0
Name: genprimers
Version: 0.0.1
Summary: A software to design PCR primers for a a subset of  sequences which belong to a greater set
Home-page: https://bitbucket.org/lbmg/genprimers
Author: Diego Diaz Dominguez
Author-email: ddiaz@dim.uchile.cl
License: BSD
Keywords: PCR primers designer
Platform: UNKNOWN
Classifier: Development Status :: 3 - Alpha
Classifier: License :: OSI Approved :: BSD License
Classifier: Programming Language :: Python :: 2.7
Classifier: Topic :: Scientific/Engineering :: Bio-Informatics
Requires-Dist: biopython (==1.68)
Requires-Dist: primer3-py (==0.5.1)
Requires-Dist: plotly (==2.0.2)
Requires-Dist: Jinja2 (==2.9.5)
